kilopa/__init__.py
kilopa/admin_server.py
kilopa/config.py
kilopa/protection.py
kilopa-0.0.1.dist-info/licenses/LICENSE
tests/__init__.py
tests/test_kilopa.py
kilopa-0.0.1.dist-info/METADATA
kilopa-0.0.1.dist-info/WHEEL
kilopa-0.0.1.dist-info/entry_points.txt
kilopa-0.0.1.dist-info/top_level.txt
kilopa-0.0.1.dist-info/RECORD
